OscilloWatch/EMD.py
OscilloWatch/HHT.py
OscilloWatch/OWSettings.py
OscilloWatch/RealTimeAnalysis.py
OscilloWatch/SegmentAnalysis.py
OscilloWatch/SignalSnapshotAnalysis.py
OscilloWatch/__init__.py
OscilloWatch/csv_column_to_list.py
OscilloWatch/post_processing.py
oscillowatch-0.1.0.dist-info/METADATA
oscillowatch-0.1.0.dist-info/WHEEL
oscillowatch-0.1.0.dist-info/licenses/LICENSE
oscillowatch-0.1.0.dist-info/RECORD
