Metadata-Version: 2.3
Name: OscilloWatch
Version: 0.1.0
Summary: PMU data monitoring tool for giving early warnings for low-frequency oscillations in power systems.
Project-URL: Homepage, https://github.com/MauritsMolberg/OscilloWatch
Project-URL: Issues, https://github.com/MauritsMolberg/OscilloWatch/issues
Author-email: Maurits Sørensen Molberg <maurits.molberg@hotmail.com>
License:                     GNU GENERAL PUBLIC LICENSE
License-File: LICENSE
Classifier: Operating System :: OS Independent
Classifier: Programming Language :: Python :: 3
Requires-Python: >=3.10
Requires-Dist: matplotlib
Requires-Dist: numpy
Requires-Dist: scipy
